{
  "cxInfo": {
    "agentCode": "",
    "checkCode": "",
    "checkNo": "",
    "commodityNo": "",
    "comparyCode": "",
    "customerId": "",
    "cxCarMessage": {
      "carName": "雪佛兰SGM7166ATB天地版",
      "carplace": "",
      "certificateDate": null,
      "certificateNo": "",
      "certificateType": "",
      "certificateTypeName": "",
      "citycode": "3320600",
      "companyCode": "",
      "createdBy": "",
      "currentvalue": 66526.6,
      "dateCreated": null,
      "dateUpdated": null,
      "drivearea": "0",
      "ecdemicVehicleFlag": "0",
      "engineNo": "112110760",
      "enginecapacity": "1598",
      "familyCarCount": "0",
      "fuelType": "",
      "fuelTypeName": "",
      "id": 15077,
      "isHaveGps": "0",
      "isocr": "",
      "jingyouFamilyname": "科鲁兹",
      "jingyouPrice": "115900",
      "jingyouVehicleCode": "KLD1009SHT",
      "jingyouVehicleName": "雪佛兰SGM7166ATB轿车",
      "licensecolor": "",
      "licensetype": "",
      "loanvehicleflag": "",
      "noticeType": "SGM7166ATB",
      "producingarea": "合资车",
      "rackNo": "LSGPC52U0BF088376",
      "registerDate": {
        "date": 11,
        "day": 2,
        "hours": 0,
        "minutes": 0,
        "month": 9,
        "seconds": 0,
        "time": 1318262400000,
        "timezoneOffset": -480,
        "year": 111
      },
      "remark": "",
      "runMileRate": "3000",
      "seats": "5.0",
      "sessionid": "17100915591131401329",
      "transferDate": {
        "date": 1,
        "day": 6,
        "hours": 0,
        "minutes": 0,
        "month": 0,
        "seconds": 0,
        "time": 946656000000,
        "timezoneOffset": -480,
        "year": 100
      },
      "transferFlag": "0",
      "updatedBy": "",
      "vehicleBrand": "雪佛兰SGM7166ATB轿车",
      "vehicleValue": 115900,
      "vehiclehycode": "BTYOKMUC0014",
      "vehicleid": "KLD1009SHT",
      "vehicleinvoicedate": {
        "date": 11,
        "day": 2,
        "hours": 0,
        "minutes": 0,
        "month": 9,
        "seconds": 0,
        "time": 1318262400000,
        "timezoneOffset": -480,
        "year": 111
      },
      "vehicleinvoiceno": "",
      "vehiclepurpose": "",
      "wholeWeight": "1390"
    },
    "cxDuty": null,
    "cxDutyDetail": null,
    "cxOffer": {
      "appointrepairCoverage": "0",
      "appointrepairFlag": "不投保",
      "appointrepairPre": 0,
      "businessBegindate": {
        "date": 10,
        "day": 2,
        "hours": 0,
        "minutes": 0,
        "month": 9,
        "seconds": 0,
        "time": 1507564800000,
        "timezoneOffset": -480,
        "year": 117
      },
      "businessEnddate": {
        "date": 9,
        "day": 2,
        "hours": 0,
        "minutes": 0,
        "month": 9,
        "seconds": 0,
        "time": 1539014400000,
        "timezoneOffset": -480,
        "year": 118
      },
      "businessPre": 2599.49,
      "carDamagerCoverage": "",
      "carDamagerFlag": "",
      "carDamagerPre": 0,
      "carlossCoverage": "66526",
      "carlossFlag": "投保",
      "carlossMpCoverage": "1",
      "carlossMpFlag": "投保",
      "carlossMpPre": 162.29,
      "carlossPre": 1081.91,
      "carscrachCoverage": "0",
      "carscrachFlag": "不投保",
      "carscrachMpCoverage": "0",
      "carscrachMpFlag": "不投保",
      "carscrachMpPre": 0,
      "carscrachPre": 0,
      "companyCode": "00004",
      "createdBy": "",
      "dateCreated": null,
      "dateUpdated": null,
      "driverCoverage": "10000元/座",
      "driverFlag": "1万/座",
      "driverMpCoverage": "1",
      "driverMpFlag": "投保",
      "driverMpPre": 3.25,
      "driverPre": 21.68,
      "glassCoverage": "0",
      "glassFlag": "不投保",
      "glassPre": 0,
      "hxFinalRetentionTime": null,
      "hxHoldTime": null,
      "id": 58422,
      "jqxBegindate": {
        "date": 10,
        "day": 2,
        "hours": 0,
        "minutes": 0,
        "month": 9,
        "seconds": 0,
        "time": 1507564800000,
        "timezoneOffset": -480,
        "year": 117
      },
      "jqxEnddate": {
        "date": 9,
        "day": 2,
        "hours": 0,
        "minutes": 0,
        "month": 9,
        "seconds": 0,
        "time": 1539014400000,
        "timezoneOffset": -480,
        "year": 118
      },
      "jqxFlag": "投保",
      "jqxPre": 665,
      "lastclaimtext": "",
      "mentaldistressCoverage": "0",
      "mentaldistressFlag": "不投保",
      "mentaldistressMpCoverage": "0",
      "mentaldistressMpFlag": "不投保",
      "mentaldistressMpPre": 0,
      "mentaldistressPre": 0,
      "newEquipmentCoverage": "0",
      "newEquipmentFlag": "不投保",
      "newEquipmentMpCoverage": "0",
      "newEquipmentMpFlag": "不投保",
      "newEquipmentMpPre": 0,
      "newEquipmentPre": 0,
      "nothirdpartyCoverage": "0",
      "nothirdpartyFlag": "不投保",
      "nothirdpartyMpFlag": "",
      "nothirdpartyMpPre": 0,
      "nothirdpartyPre": 0,
      "orderNo": "17100916012274184242",
      "passengerCoverage": "10000元/座",
      "passengerFlag": "1万/座",
      "passengerMpCoverage": "1",
      "passengerMpFlag": "投保",
      "passengerMpPre": 8.45,
      "passengerPre": 56.36,
      "productId": "",
      "remark": "",
      "selfigniteCoverage": "0",
      "selfigniteFlag": "不投保",
      "selfigniteMpCoverage": "0",
      "selfigniteMpFlag": "不投保",
      "selfigniteMpPre": 0,
      "selfignitePre": 0,
      "sessionid": "17100915591131401329",
      "spiritdamageCoverage": "",
      "spiritdamageFlag": "",
      "spiritdamagePre": 0,
      "standardpremium": 0,
      "theftCoverage": "66526",
      "theftFlag": "投保",
      "theftMpCoverage": "1",
      "theftMpFlag": "投保",
      "theftMpPre": 43.29,
      "theftPre": 216.44,
      "thirdpartyCoverage": "500000",
      "thirdpartyFlag": "50万",
      "thirdpartyMpCoverage": "1",
      "thirdpartyMpFlag": "投保",
      "thirdpartyMpPre": 131.19,
      "thirdpartyPre": 874.63,
      "totalPre": 3564.49,
      "totalpremium": 3564.49,
      "updatedBy": "",
      "vehicletaxBegindate": null,
      "vehicletaxEnddate": null,
      "vehicletaxFlag": "",
      "vehicletaxPre": 300,
      "wadingCoverage": "0",
      "wadingFlag": "不投保",
      "wadingMpCoverage": "0",
      "wadingMpFlag": "不投保",
      "wadingMpPre": 0,
      "wadingPre": 0
    },
    "cxOrder": {
      "acceptDate": null,
      "addresseecity": "",
      "addresseecitycode": "",
      "addresseeprovince": "江苏省南通",
      "addresseeprovincecode": "",
      "addresseetown": "",
      "addresseetowncode": "",
      "agentId": 0,
      "appno": "0613500136320170004445",
      "buinsurancequerycode": "30ab528b102d4ef3988be135cf49806b",
      "businessAppno": "0613500080820170004624",
      "businessPolno": "6613530080820170005516",
      "cdCityCode": "",
      "cdCityName": "",
      "cdName": "",
      "cdProvinceCode": "",
      "cdProvinceName": "",
      "cdWorkno": "",
      "certiEnddate": null,
      "certiStartdate": null,
      "checkcode": "anxf",
      "checkno": "72TAIC320017001507536035904201",
      "cityCode": "3320600",
      "cityName": "江苏省-南通",
      "commodityName": "老司机套餐",
      "commodityNo": "0419900103",
      "companyCode": "00004",
      "createdBy": "",
      "customerId": 0,
      "cxOrgaddid": 0,
      "dateCreated": {
        "date": 9,
        "day": 1,
        "hours": 15,
        "minutes": 59,
        "month": 9,
        "seconds": 11,
        "time": 1507535951000,
        "timezoneOffset": -480,
        "year": 117
      },
      "dateUpdated": {
        "date": 10,
        "day": 2,
        "hours": 5,
        "minutes": 0,
        "month": 9,
        "seconds": 1,
        "time": 1507582801000,
        "timezoneOffset": -480,
        "year": 117
      },
      "effectiveDate": null,
      "elrLevelAll": "c3",
      "elrLevelCom": "b3",
      "elrLevelCtp": "d3",
      "exclusiveCode": "AA",
      "exclusiveName": "老司机套餐",
      "flag": "",
      "flag1": "",
      "forceAppno": "0613500080120170004467",
      "forcePolno": "6613530080120170005486",
      "handleTime": null,
      "hzCityCode": "",
      "hzCityName": "",
      "hzCompanyCode": "",
      "hzCompanyName": "",
      "hzName": "",
      "hzNote": "",
      "hzPhone": "",
      "hzProvinceCode": "",
      "hzProvinceName": "",
      "hzWorkno": "",
      "id": 16357,
      "insertTime": {
        "date": 9,
        "day": 1,
        "hours": 15,
        "minutes": 59,
        "month": 9,
        "seconds": 11,
        "time": 1507535951000,
        "timezoneOffset": -480,
        "year": 117
      },
      "insureDate": {
        "date": 9,
        "day": 1,
        "hours": 16,
        "minutes": 2,
        "month": 9,
        "seconds": 48,
        "time": 1507536168000,
        "timezoneOffset": -480,
        "year": 117
      },
      "insuredidaddress": "",
      "isRepeat": "",
      "issueChannel": "11",
      "issuerAuthority": "",
      "jqinsurancequerycode": "",
      "litigationarbitration": "",
      "modifyTime": {
        "date": 9,
        "day": 1,
        "hours": 16,
        "minutes": 4,
        "month": 9,
        "seconds": 37,
        "time": 1507536277000,
        "timezoneOffset": -480,
        "year": 117
      },
      "nation": "",
      "newcarFlag": "0",
      "openId": "",
      "orderChannel": "1",
      "orderNo": "17100916012274184242",
      "orderStatus": "10",
      "ownerEmail": "",
      "ownerIdno": "320682199107060680",
      "ownerMobile": "15162754099",
      "ownerName": "孟牡丹",
      "ownerNaturetype": "",
      "payCheckcode": "",
      "payUrl": "http: //www.95505.cn/tianan_cpf/common/pay/applyPay.do?orderNo\u003djUneBUTj\u0026pageUrl\u003dhttps: //td-pro.ta-by.com/tongdaoPlatform/weixin/wxcar/html/carinsure/payResoltWX.html?orderNo\u003d17100916012274184242\u0026payType\u003d7",
      "payappno": "",
      "paymentenddate": {
        "date": 9,
        "day": 1,
        "hours": 16,
        "minutes": 4,
        "month": 9,
        "seconds": 27,
        "time": 1507536267000,
        "timezoneOffset": -480,
        "year": 117
      },
      "payments": "移动支付",
      "plateno": "苏F30T85",
      "policyForm": "",
      "policyRisk": "",
      "polno": "6613530136320170004729",
      "productCode": "",
      "provinceCode": "8",
      "provinceName": "江苏省",
      "psAddress": "如皋市万寿南路999号软件园1号楼310",
      "refuseReason": "确认投保成功！提交核保成功！。核保返回具体信息：[   \"1\":\"私家车商业险，自核通过\"; ]",
      "registerFlag": "",
      "remark": "",
      "remarkCon": "0161353018",
      "senddate": null,
      "sessionid": "17100915591131401329",
      "sjrEmail": "",
      "sjrMobile": "15162754099",
      "sjrName": "孟牡丹",
      "sjrZipcode": 0,
      "tradeno": "jUneBUTj",
      "underwriteDate": {
        "date": 9,
        "day": 1,
        "hours": 16,
        "minutes": 4,
        "month": 9,
        "seconds": 37,
        "time": 1507536277000,
        "timezoneOffset": -480,
        "year": 117
      },
      "undwrtTime": {
        "date": 9,
        "day": 1,
        "hours": 16,
        "minutes": 2,
        "month": 9,
        "seconds": 48,
        "time": 1507536168000,
        "timezoneOffset": -480,
        "year": 117
      },
      "updatedBy": "",
      "userName": "S2IDH2017100900002",
      "usercode": "",
      "vehiclemodeldata": "eyJ2ZWhpY2xlTW9kZWxEYXRhIjp7ImFjdHVhbFZhbHVlIjo2NjUyNi42LCJicmFuZE5hbWUiOiLpm6rkvZvlhbBTR003MTY2QVRC6L2/6L2mIiwiY2FyTmFtZSI6IumbquS9m+WFsFNHTTcxNjZBVEIg5aSp5Zyw54mIIiwiZWNkZW1pY1ZlaGljbGVGbGFnIjoiMCIsImV4aGF1c3RDYXBhY2l0eSI6MTU5OCwiaHlNb2RlbENvZGUiOiJCVFlPS01VQzAwMTQiLCJpbXBvcnRGbGFnIjoi5ZCI6LWE6L2mIiwibWFya2V0RGF0ZSI6IjIwMTAwOCIsIm5vdGljZVR5cGUiOiJTR003MTY2QVRCIiwicHVyY2hhc2VQcmljZSI6MTE1OTAwLCJyYmNvZGUiOiJLTEQxMDA5U0hUIiwic2VhdENvdW50Ijo1LCJ2ZWhpY2xlSmluZ3lvdUR0byI6eyJicmFuZE5hbWUiOiLkuIrmsb3pgJrnlKjpm6rkvZvlhbAiLCJmYW1pbHlOYW1lIjoi56eR6bKB5YW5IiwicHJpY2UiOjExNTkwMCwicHJpY2VUeXBlIjoiMDEiLCJ2ZWhpY2xlQ29kZSI6IktMRDEwMDlTSFQiLCJ2ZWhpY2xlTmFtZSI6IumbquS9m+WFsFNHTTcxNjZBVELovb/ovaYifSwidmVoaWNsZVN0eWxlRGVzYyI6IuaJi+iHquS4gOS9kyBTTCDlpKnlnLDniYgg5Zu94oWjICjoioLog73ooaXotLQpIiwidmVoaWNsZVRvbm5hZ2UiOjAsInZlaGljbGVXZWlnaHQiOjEzOTB9fQ\u003d\u003d",
      "vehiclepurpose": "",
      "vehicleusage1": "",
      "vehicleusage2": "",
      "vehiclevariety1": "",
      "vehiclevariety2": ""
    },
    "cxOrderOrgadd": null,
    "cxParty": {
      "beneType": "",
      "beneadress": "",
      "benebirthdate": null,
      "beneemail": "",
      "benegender": "",
      "beneidno": "",
      "beneidtype": "",
      "benemobile": "",
      "benename": "",
      "benenaturetype": "",
      "companyCode": "",
      "createdBy": "",
      "dateCreated": null,
      "dateUpdated": null,
      "driverName": "",
      "driverTrueFlag": "",
      "drivingLicence": "",
      "gender": "2",
      "id": 26412,
      "insnatureJob": "",
      "insnatureRegisterTime": null,
      "insnaturetype": "",
      "insuredadress": "江苏省 南通 如皋市万寿南路999号软件园1号楼310",
      "insuredbirthdate": {
        "date": 6,
        "day": 6,
        "hours": 0,
        "minutes": 0,
        "month": 6,
        "seconds": 0,
        "time": 678726000000,
        "timezoneOffset": -540,
        "year": 91
      },
      "insuredemail": "",
      "insuredenddate": null,
      "insuredgender": "2",
      "insuredidno": "320682199107060680",
      "insuredidtype": "01",
      "insuredissuer": "",
      "insuredmobile": "15162754099",
      "insuredname": "孟牡丹",
      "insurednation": "",
      "insuredstartdate": null,
      "orderNo": "17100916012274184242",
      "phaddress": "江苏省 南通 如皋市万寿南路999号软件园1号楼310",
      "phbirthdate": {
        "date": 6,
        "day": 6,
        "hours": 0,
        "minutes": 0,
        "month": 6,
        "seconds": 0,
        "time": 678726000000,
        "timezoneOffset": -540,
        "year": 91
      },
      "phemail": "",
      "phenddate": null,
      "phidno": "320682199107060680",
      "phidtype": "01",
      "phissuer": "",
      "phname": "孟牡丹",
      "phnation": "",
      "phstartdate": null,
      "phtelephone": "15162754099",
      "pnaturetype": "",
      "remark": "",
      "sessionid": "17100915591131401329",
      "updatedBy": ""
    },
    "elrLevelAll": "",
    "elrLevelCOM": "",
    "elrLevelCTP": "",
    "exclusiveCode": "",
    "exclusiveName": "",
    "fgFlag": "",
    "hqCommision": "",
    "issueChannel": "",
    "openId": "",
    "orderChannel": "",
    "orgCommision": "",
    "productId": "",
    "sessionId": "",
    "tradeNO": "",
    "transToken": "",
    "vehicleModelData": ""
  },
  "cxRiskInfoList": {
    "add": [

    ],
    "all": [
      {
        "coverage": "1",
        "flag": "投保",
        "name": "机动车损失险不计免赔",
        "pre": "162.29"
      },
      {
        "coverage": "1",
        "flag": "投保",
        "name": "第三者责任险不计免赔",
        "pre": "131.19"
      },
      {
        "coverage": "1",
        "flag": "投保",
        "name": "驾驶人责任险不计免赔",
        "pre": "3.25"
      },
      {
        "coverage": "1",
        "flag": "投保",
        "name": "乘客责任险不计免赔",
        "pre": "8.45"
      },
      {
        "coverage": "1",
        "flag": "投保",
        "name": "全车盗抢险不计免赔",
        "pre": "43.29"
      }
    ],
    "cxPriservices": [
      {
        "createdBy": "",
        "dateCreated": null,
        "dateUpdated": null,
        "id": 1,
        "remark": "",
        "serviceInfo": "\u003cp\u003e被保险车辆如发生3000元以下且不涉及人伤的保险事故，经我司定损确认后，仅需驾驶证、行驶证、身份证、银行卡、事故证明材料（免证明案件除外）、维修发票（免发票案件除外）即可办理理赔。\u003c\/p\u003e",
        "serviceTitle": "小额快赔",
        "updatedBy": ""
      },
      {
        "createdBy": "",
        "dateCreated": null,
        "dateUpdated": null,
        "id": 2,
        "remark": "",
        "serviceInfo": "\u003cp\u003e在非保单承保地区出险，您可享受在出险当地办理查勘、定损、送交理赔材料、领取赔款等理赔流程。具体公司服务网点可咨询全国统一客服电话95505或登录公司官网首页查询。\u003c\/p\u003e",
        "serviceTitle": "全国通赔",
        "updatedBy": ""
      },
      {
        "createdBy": "",
        "dateCreated": null,
        "dateUpdated": null,
        "id": 3,
        "remark": "",
        "serviceInfo": "\u003cp\u003e您可享受我司全国365天*24小时免费非事故汽车道路救援服务。\u003c\/p\u003e",
        "serviceTitle": "非事故道路救援",
        "updatedBy": ""
      },
      {
        "createdBy": "",
        "dateCreated": null,
        "dateUpdated": null,
        "id": 4,
        "remark": "",
        "serviceInfo": "\u003cp\u003e如您的爱车是9座及以下的，在事故定损维修过程中，经被保险人、修理厂和保险公司三方协商确认需更换的零配件，我司可根据您的要求对车辆维修后零配件是否更换进行检验。\u003c\/p\u003e\r\n     \u003cp\u003e你修车我检验流程：\u003c\/p\u003e\r\n     \u003cp\u003e（1）您可通过直接拨打95505，选择1号键进行预约，或通过扫码关注“天安直通车险”微信号--\u003e服务中心“你修车我检验” --\u003e填写“车牌+手机”进行预约；\u003c\/p\u003e\r\n     \u003cp\u003e（2）95505客服人员将登记您的信息，安排检验人员为您服务；\u003c\/p\u003e\r\n     \u003cp\u003e（3）检验人员将与您电话预约时间、地点，进行检验服务。\u003c\/p\u003e",
        "serviceTitle": "你修车我检验",
        "updatedBy": ""
      },
      {
        "createdBy": "",
        "dateCreated": null,
        "dateUpdated": null,
        "id": 5,
        "remark": "",
        "serviceInfo": "\u003cp\u003e投保后，您可至我司官网下载车易赔APP，即可享受掌上理赔服务。\u003c\/p\u003e",
        "serviceTitle": "车易赔掌上服务",
        "updatedBy": ""
      },
      {
        "createdBy": "",
        "dateCreated": null,
        "dateUpdated": null,
        "id": 8,
        "remark": "",
        "serviceInfo": "\u003cp\u003e（1）被保险车辆发生单方事故，在不涉及人员伤亡及第三方财产损失的，仅本车外观件、车身漆面受损的，经我司第一现场查勘无误的，可免开具事故证明。\u003c\/p\u003e\r\n     \u003cp\u003e（2）被保险车辆发生单方事故，不涉及人员伤亡及第三方财产损失，仅本车外观件、车身漆面受损的，客户报案后第一现场拍摄照片，并通过微信等方式通知我司理赔人员，经我司人员确认允许离开现场，且损失金额2000元以内的，可免开具事故证明。\r\n\u003c\/p\u003e",
        "serviceTitle": "免事故证明（非车易赔）",
        "updatedBy": ""
      },
      {
        "createdBy": "",
        "dateCreated": null,
        "dateUpdated": null,
        "id": 9,
        "remark": "",
        "serviceInfo": "\u003cp\u003e使用车易赔掌上服务的客户，被保险车辆发生单方事故，在第一现场报案后，通过车易赔客户端视频连线，可免除等待理赔人员现场查勘，且无需提供事故证明。\u003c\/p\u003e\r\n     \u003cp\u003e服务条件：\u003c\/p\u003e\r\n     \u003cp\u003e（1）仅发生单方碰撞事故，不涉及人员伤亡及第三方财产损失的；\u003c\/p\u003e\r\n     \u003cp\u003e（2）仅车辆外观件、车身漆面受损；（车辆外观件是指：前后保险杠、前后翼子板、发动机罩、后行李箱盖、车顶、车门、前照灯、后尾灯）\u003c\/p\u003e\r\n     \u003cp\u003e（3）在我公司理赔人员指导下，使用车易赔客户端视频连线，经我司理赔人员确认的案件。\r\n\u003c\/p\u003e",
        "serviceTitle": "车易赔免事故现场、事故证明",
        "updatedBy": ""
      },
      {
        "createdBy": "",
        "dateCreated": null,
        "dateUpdated": null,
        "id": 13,
        "remark": "",
        "serviceInfo": "\u003cp\u003e提供包括：\u003c\/p\u003e\r\n     \u003cp\u003e（1）从报案起全流程理赔程序、理赔资料及理赔处理等指导；\u003c\/p\u003e\r\n     \u003cp\u003e（2）住院、伤残评定等阶段的咨询和建议；\u003c\/p\u003e\r\n     \u003cp\u003e（3）事故处理、诉讼相关法律法规咨询和建议。\u003c\/p\u003e\r\n     \u003cp\u003e服务条件：通过95505报案的车险人伤案件。\r\n\u003c\/p\u003e",
        "serviceTitle": "人伤理赔全程指引",
        "updatedBy": ""
      }
    ],
    "main": [
      {
        "coverage": "66526",
        "flag": "投保",
        "name": "机动车损失险",
        "pre": "1081.91"
      },
      {
        "coverage": "500000",
        "flag": "50万",
        "name": "第三者责任险",
        "pre": "874.63"
      },
      {
        "coverage": "10000元/座",
        "flag": "1万/座",
        "name": "驾驶人责任险",
        "pre": "21.68"
      },
      {
        "coverage": "10000元/座",
        "flag": "1万/座",
        "name": "乘客责任险",
        "pre": "56.36"
      },
      {
        "coverage": "66526",
        "flag": "投保",
        "name": "全车盗抢险",
        "pre": "216.44"
      }
    ]
  },
  "status": {
    "channel": "",
    "returns": {

    },
    "statusCode": "000000",
    "statusMessage": "",
    "transTime": "",
    "transToken": "",
    "userCode": ""
  }
}